<!-- == AutoIt == -->
<LexerType name="autoit" desc="AutoIt" ext="au3">
  <WordsStyle name="DEFAULT" styleID="0" fgColor="E4E8E8" bgColor="2A2A2B" fontStyle="0"/>
  <WordsStyle name="COMMENT LINE" styleID="1" fgColor="626262" bgColor="2A2A2B" fontStyle="0"/>
  <WordsStyle name="COMMENT" styleID="2" fgColor="626262" bgColor="2A2A2B" fontStyle="0"/>
  <WordsStyle name="NUMBER" styleID="3" fgColor="A074C4" bgColor="2A2A2B" fontStyle="0"/>
  <WordsStyle name="FUNCTION" styleID="4" fgColor="9FCA56" bgColor="2A2A2B" fontStyle="0" keywordClass="instre2"/>
  <!-- <WordsStyle name="INSTRUCTION WORD" styleID="5" fgColor="6897BB" bgColor="2A2A2B" fontStyle="0" keywordClass="instre1"/> -->
  <!-- <WordsStyle name="MACRO" styleID="6" fgColor="CB4B16" bgColor="2A2A2B" fontStyle="0" keywordClass="type1"/> -->
  <WordsStyle name="STRING" styleID="7" fgColor="B5CEA8" bgColor="2A2A2B" fontStyle="0"/>
  <WordsStyle name="OPERATOR" styleID="8" fgColor="6897BB" bgColor="2A2A2B" fontStyle="0"/>
  <WordsStyle name="VARIABLE" styleID="9" fgColor="E4E8E8" bgColor="2A2A2B" fontStyle="0"/>
  <!-- <WordsStyle name="SENT" styleID="10" fgColor="CB4B16" bgColor="2A2A2B" fontStyle="0" keywordClass="type2"/> -->
  <!-- <WordsStyle name="PREPROCESSOR" styleID="11" fgColor="DC322F" bgColor="2A2A2B" fontStyle="0" keywordClass="type3"/> -->
  <!-- <WordsStyle name="SPECIAL" styleID="12" fgColor="93A1A1" bgColor="2A2A2B" fontStyle="0" keywordClass="type4"/> -->
  <!-- <WordsStyle name="EXPAND" styleID="13" fgColor="DC322F" bgColor="2A2A2B" fontStyle="0" keywordClass="type5"/> -->
  <!-- <WordsStyle name="COMOBJ" styleID="14" fgColor="268BD2" bgColor="2A2A2B" fontStyle="0"/> -->
</LexerType>